wagtailblocks_cards/__init__.py
wagtailblocks_cards/blocks.py
wagtailblocks_cards/static/wagtailblocks_cards/css/wagtailblocks_cards.css
wagtailblocks_cards/templates/wagtailblocks_cards/block_forms/cards.html
wagtailblocks_cards-2.1.0.dist-info/DESCRIPTION.rst
wagtailblocks_cards-2.1.0.dist-info/METADATA
wagtailblocks_cards-2.1.0.dist-info/RECORD
wagtailblocks_cards-2.1.0.dist-info/WHEEL
wagtailblocks_cards-2.1.0.dist-info/metadata.json
wagtailblocks_cards-2.1.0.dist-info/top_level.txt
