Metadata-Version: 2.0
Name: wagtailblocks-cards
Version: 2.1.0
Summary: A simple list of cards.
Home-page: https://github.com/alexgleason/wagtailblocks_cards
Author: Alex Gleason
Author-email: alex@alexgleason.me
License: MIT
Keywords: development
Platform: UNKNOWN
Classifier: Environment :: Web Environment
Classifier: Framework :: Django
Classifier: Intended Audience :: Developers
Classifier: Operating System :: OS Independent
Classifier: Programming Language :: Python
Classifier: Topic :: Internet :: WWW/HTTP
Classifier: Topic :: Internet :: WWW/HTTP :: Dynamic Content
Requires-Dist: Django (>=1.7.1)
Requires-Dist: wagtail (>=0.8.7)
